app/__init__.py
app/main.py
app/pyinstaller.py
m3uprsr-0.1.36.dist-info/LICENSE
m3uprsr-0.1.36.dist-info/METADATA
m3uprsr-0.1.36.dist-info/WHEEL
m3uprsr-0.1.36.dist-info/entry_points.txt
m3uprsr-0.1.36.dist-info/RECORD
